tbtPythonTool/__init__.py
tbtPythonTool/mainTBT.py
tbtPythonTool-1.0.0.dist-info/METADATA
tbtPythonTool-1.0.0.dist-info/WHEEL
tbtPythonTool-1.0.0.dist-info/top_level.txt
tbtPythonTool-1.0.0.dist-info/RECORD
