Metadata-Version: 2.1
Name: tbtPythonTool
Version: 1.0.0
Summary: TBT package on gitlab
Home-page: https://gitlabe2.ext.net.nokia.com/shaldixi/datsv.git
Author: Shalini Dixit
Author-email: shalinidxt0@gmail.com
License: UNKNOWN
Platform: UNKNOWN
